{"numTotalTestSuites":4,"numPassedTestSuites":2,"numFailedTestSuites":2,"numPendingTestSuites":0,"numTotalTests":44,"numPassedTests":39,"numFailedTests":5,"numPendingTests":0,"numTodoTests":0,"snapshot":{"added":0,"failure":false,"filesAdded":0,"filesRemoved":0,"filesRemovedList":[],"filesUnmatched":0,"filesUpdated":0,"matched":0,"total":0,"unchecked":0,"uncheckedKeysByFile":[],"unmatched":0,"updated":0,"didUpdate":false},"startTime":1776098660411,"success":false,"testResults":[{"assertionResults":[{"ancestorTitles":["Exercício 01"],"fullName":"Exercício 01 Ex01 - Válida - Questão 1","status":"passed","title":"Ex01 - Válida - Questão 1","duration":1.2154449999999883,"failureMessages":[],"meta":{}},{"ancestorTitles":["Exercício 01"],"fullName":"Exercício 01 Ex01 - Correta - Questão 1","status":"passed","title":"Ex01 - Correta - Questão 1","duration":0.6869059999999934,"failureMessages":[],"meta":{}},{"ancestorTitles":["Exercício 01"],"fullName":"Exercício 01 Ex01 - Válida - Questão 2","status":"passed","title":"Ex01 - Válida - Questão 2","duration":0.17260500000000434,"failureMessages":[],"meta":{}},{"ancestorTitles":["Exercício 01"],"fullName":"Exercício 01 Ex01 - Correta - Questão 2","status":"passed","title":"Ex01 - Correta - Questão 2","duration":0.32580100000001266,"failureMessages":[],"meta":{}},{"ancestorTitles":["Exercício 01"],"fullName":"Exercício 01 Ex01 - Válida - Questão 3","status":"passed","title":"Ex01 - Válida - Questão 3","duration":0.16985000000002515,"failureMessages":[],"meta":{}},{"ancestorTitles":["Exercício 01"],"fullName":"Exercício 01 Ex01 - Correta - Questão 3","status":"passed","title":"Ex01 - Correta - Questão 3","duration":0.10786600000000135,"failureMessages":[],"meta":{}},{"ancestorTitles":["Exercício 01"],"fullName":"Exercício 01 Ex01 - Válida - Questão 4","status":"passed","title":"Ex01 - Válida - Questão 4","duration":0.18146300000000792,"failureMessages":[],"meta":{}},{"ancestorTitles":["Exercício 01"],"fullName":"Exercício 01 Ex01 - Correta - Questão 4","status":"passed","title":"Ex01 - Correta - Questão 4","duration":0.12008399999999142,"failureMessages":[],"meta":{}},{"ancestorTitles":["Exercício 01"],"fullName":"Exercício 01 Ex01 - Válida - Questão 5","status":"passed","title":"Ex01 - Válida - Questão 5","duration":0.28848800000000097,"failureMessages":[],"meta":{}},{"ancestorTitles":["Exercício 01"],"fullName":"Exercício 01 Ex01 - Correta - Questão 5","status":"passed","title":"Ex01 - Correta - Questão 5","duration":0.28398200000000884,"failureMessages":[],"meta":{}},{"ancestorTitles":["Exercício 01"],"fullName":"Exercício 01 Ex01 - Válida - Questão 6","status":"passed","title":"Ex01 - Válida - Questão 6","duration":0.16951899999997977,"failureMessages":[],"meta":{}},{"ancestorTitles":["Exercício 01"],"fullName":"Exercício 01 Ex01 - Correta - Questão 6","status":"passed","title":"Ex01 - Correta - Questão 6","duration":0.10408700000002113,"failureMessages":[],"meta":{}},{"ancestorTitles":["Exercício 01"],"fullName":"Exercício 01 Ex01 - Válida - Questão 7","status":"passed","title":"Ex01 - Válida - Questão 7","duration":0.09362200000001053,"failureMessages":[],"meta":{}},{"ancestorTitles":["Exercício 01"],"fullName":"Exercício 01 Ex01 - Correta - Questão 7","status":"passed","title":"Ex01 - Correta - Questão 7","duration":0.15400399999998626,"failureMessages":[],"meta":{}},{"ancestorTitles":["Exercício 01"],"fullName":"Exercício 01 Ex01 - Válida - Questão 8","status":"passed","title":"Ex01 - Válida - Questão 8","duration":0.09460400000000391,"failureMessages":[],"meta":{}},{"ancestorTitles":["Exercício 01"],"fullName":"Exercício 01 Ex01 - Correta - Questão 8","status":"passed","title":"Ex01 - Correta - Questão 8","duration":0.08865900000000693,"failureMessages":[],"meta":{}},{"ancestorTitles":["Exercício 01"],"fullName":"Exercício 01 Ex01 - Válida - Questão 9","status":"passed","title":"Ex01 - Válida - Questão 9","duration":0.09060099999999238,"failureMessages":[],"meta":{}},{"ancestorTitles":["Exercício 01"],"fullName":"Exercício 01 Ex01 - Correta - Questão 9","status":"passed","title":"Ex01 - Correta - Questão 9","duration":0.07846399999999676,"failureMessages":[],"meta":{}},{"ancestorTitles":["Exercício 01"],"fullName":"Exercício 01 Ex01 - Válida - Questão 10","status":"passed","title":"Ex01 - Válida - Questão 10","duration":0.09283599999997705,"failureMessages":[],"meta":{}},{"ancestorTitles":["Exercício 01"],"fullName":"Exercício 01 Ex01 - Correta - Questão 10","status":"passed","title":"Ex01 - Correta - Questão 10","duration":0.07383899999999244,"failureMessages":[],"meta":{}}],"startTime":1776098660582,"endTime":1776098660587.154,"status":"passed","message":"","name":"/home/vmca/Code/school/atv_pub/2d-04-lacos/ex01.test.js"},{"assertionResults":[{"ancestorTitles":["Exercício 02"],"fullName":"Exercício 02 Ex02 - Válida - Questão 1","status":"passed","title":"Ex02 - Válida - Questão 1","duration":1.478161,"failureMessages":[],"meta":{}},{"ancestorTitles":["Exercício 02"],"fullName":"Exercício 02 Ex02 - Correta - Questão 1","status":"passed","title":"Ex02 - Correta - Questão 1","duration":0.6292349999999942,"failureMessages":[],"meta":{}},{"ancestorTitles":["Exercício 02"],"fullName":"Exercício 02 Ex02 - Válida - Questão 2","status":"passed","title":"Ex02 - Válida - Questão 2","duration":0.17405600000000732,"failureMessages":[],"meta":{}},{"ancestorTitles":["Exercício 02"],"fullName":"Exercício 02 Ex02 - Correta - Questão 2","status":"passed","title":"Ex02 - Correta - Questão 2","duration":0.2879999999999825,"failureMessages":[],"meta":{}},{"ancestorTitles":["Exercício 02"],"fullName":"Exercício 02 Ex02 - Válida - Questão 3","status":"passed","title":"Ex02 - Válida - Questão 3","duration":0.17121900000000778,"failureMessages":[],"meta":{}},{"ancestorTitles":["Exercício 02"],"fullName":"Exercício 02 Ex02 - Correta - Questão 3","status":"passed","title":"Ex02 - Correta - Questão 3","duration":0.12470599999997489,"failureMessages":[],"meta":{}},{"ancestorTitles":["Exercício 02"],"fullName":"Exercício 02 Ex02 - Válida - Questão 4","status":"passed","title":"Ex02 - Válida - Questão 4","duration":0.18183700000000158,"failureMessages":[],"meta":{}},{"ancestorTitles":["Exercício 02"],"fullName":"Exercício 02 Ex02 - Correta - Questão 4","status":"passed","title":"Ex02 - Correta - Questão 4","duration":0.12187800000000948,"failureMessages":[],"meta":{}},{"ancestorTitles":["Exercício 02"],"fullName":"Exercício 02 Ex02 - Válida - Questão 5","status":"passed","title":"Ex02 - Válida - Questão 5","duration":0.29834499999998343,"failureMessages":[],"meta":{}},{"ancestorTitles":["Exercício 02"],"fullName":"Exercício 02 Ex02 - Correta - Questão 5","status":"passed","title":"Ex02 - Correta - Questão 5","duration":0.2713269999999852,"failureMessages":[],"meta":{}},{"ancestorTitles":["Exercício 02"],"fullName":"Exercício 02 Ex02 - Válida - Questão 6","status":"passed","title":"Ex02 - Válida - Questão 6","duration":0.11574600000000146,"failureMessages":[],"meta":{}},{"ancestorTitles":["Exercício 02"],"fullName":"Exercício 02 Ex02 - Correta - Questão 6","status":"passed","title":"Ex02 - Correta - Questão 6","duration":0.17286900000001992,"failureMessages":[],"meta":{}},{"ancestorTitles":["Exercício 02"],"fullName":"Exercício 02 Ex02 - Válida - Questão 7","status":"passed","title":"Ex02 - Válida - Questão 7","duration":0.09916700000002265,"failureMessages":[],"meta":{}},{"ancestorTitles":["Exercício 02"],"fullName":"Exercício 02 Ex02 - Correta - Questão 7","status":"passed","title":"Ex02 - Correta - Questão 7","duration":0.15596400000001154,"failureMessages":[],"meta":{}},{"ancestorTitles":["Exercício 02"],"fullName":"Exercício 02 Ex02 - Válida - Questão 8","status":"failed","title":"Ex02 - Válida - Questão 8","duration":5.401380999999986,"failureMessages":["AssertionError: expected false not to be type of 'boolean'\n    at /home/vmca/Code/school/atv_pub/2d-04-lacos/ex02.test.js:41:34\n    at file:///home/vmca/Code/school/atv_pub/2d-04-lacos/node_modules/@vitest/runner/dist/index.js:145:11\n    at file:///home/vmca/Code/school/atv_pub/2d-04-lacos/node_modules/@vitest/runner/dist/index.js:915:26\n    at file:///home/vmca/Code/school/atv_pub/2d-04-lacos/node_modules/@vitest/runner/dist/index.js:1243:20\n    at new Promise (<anonymous>)\n    at runWithTimeout (file:///home/vmca/Code/school/atv_pub/2d-04-lacos/node_modules/@vitest/runner/dist/index.js:1209:10)\n    at file:///home/vmca/Code/school/atv_pub/2d-04-lacos/node_modules/@vitest/runner/dist/index.js:1653:37\n    at Traces.$ (file:///home/vmca/Code/school/atv_pub/2d-04-lacos/node_modules/vitest/dist/chunks/traces.CCmnQaNT.js:142:27)\n    at trace (file:///home/vmca/Code/school/atv_pub/2d-04-lacos/node_modules/vitest/dist/chunks/test.B8ej_ZHS.js:239:21)\n    at runTest (file:///home/vmca/Code/school/atv_pub/2d-04-lacos/node_modules/@vitest/runner/dist/index.js:1653:12)"],"meta":{}},{"ancestorTitles":["Exercício 02"],"fullName":"Exercício 02 Ex02 - Correta - Questão 8","status":"failed","title":"Ex02 - Correta - Questão 8","duration":2.5467490000000055,"failureMessages":["AssertionError: expected false to deeply equal [ Array(15) ]\n    at /home/vmca/Code/school/atv_pub/2d-04-lacos/ex02.test.js:45:30\n    at file:///home/vmca/Code/school/atv_pub/2d-04-lacos/node_modules/@vitest/runner/dist/index.js:145:11\n    at file:///home/vmca/Code/school/atv_pub/2d-04-lacos/node_modules/@vitest/runner/dist/index.js:915:26\n    at file:///home/vmca/Code/school/atv_pub/2d-04-lacos/node_modules/@vitest/runner/dist/index.js:1243:20\n    at new Promise (<anonymous>)\n    at runWithTimeout (file:///home/vmca/Code/school/atv_pub/2d-04-lacos/node_modules/@vitest/runner/dist/index.js:1209:10)\n    at file:///home/vmca/Code/school/atv_pub/2d-04-lacos/node_modules/@vitest/runner/dist/index.js:1653:37\n    at Traces.$ (file:///home/vmca/Code/school/atv_pub/2d-04-lacos/node_modules/vitest/dist/chunks/traces.CCmnQaNT.js:142:27)\n    at trace (file:///home/vmca/Code/school/atv_pub/2d-04-lacos/node_modules/vitest/dist/chunks/test.B8ej_ZHS.js:239:21)\n    at runTest (file:///home/vmca/Code/school/atv_pub/2d-04-lacos/node_modules/@vitest/runner/dist/index.js:1653:12)"],"meta":{}},{"ancestorTitles":["Exercício 02"],"fullName":"Exercício 02 Ex02 - Válida - Questão 9","status":"passed","title":"Ex02 - Válida - Questão 9","duration":0.14537599999999884,"failureMessages":[],"meta":{}},{"ancestorTitles":["Exercício 02"],"fullName":"Exercício 02 Ex02 - Correta - Questão 9","status":"passed","title":"Ex02 - Correta - Questão 9","duration":0.11471000000000231,"failureMessages":[],"meta":{}},{"ancestorTitles":["Exercício 02"],"fullName":"Exercício 02 Ex02 - Válida - Questão 10","status":"passed","title":"Ex02 - Válida - Questão 10","duration":0.10055099999999584,"failureMessages":[],"meta":{}},{"ancestorTitles":["Exercício 02"],"fullName":"Exercício 02 Ex02 - Correta - Questão 10","status":"failed","title":"Ex02 - Correta - Questão 10","duration":2.3965860000000134,"failureMessages":["AssertionError: expected [] to deeply equal [ 'lagarto', 'tarântula', …(4) ]\n    at /home/vmca/Code/school/atv_pub/2d-04-lacos/ex02.test.js:45:30\n    at file:///home/vmca/Code/school/atv_pub/2d-04-lacos/node_modules/@vitest/runner/dist/index.js:145:11\n    at file:///home/vmca/Code/school/atv_pub/2d-04-lacos/node_modules/@vitest/runner/dist/index.js:915:26\n    at file:///home/vmca/Code/school/atv_pub/2d-04-lacos/node_modules/@vitest/runner/dist/index.js:1243:20\n    at new Promise (<anonymous>)\n    at runWithTimeout (file:///home/vmca/Code/school/atv_pub/2d-04-lacos/node_modules/@vitest/runner/dist/index.js:1209:10)\n    at file:///home/vmca/Code/school/atv_pub/2d-04-lacos/node_modules/@vitest/runner/dist/index.js:1653:37\n    at Traces.$ (file:///home/vmca/Code/school/atv_pub/2d-04-lacos/node_modules/vitest/dist/chunks/traces.CCmnQaNT.js:142:27)\n    at trace (file:///home/vmca/Code/school/atv_pub/2d-04-lacos/node_modules/vitest/dist/chunks/test.B8ej_ZHS.js:239:21)\n    at runTest (file:///home/vmca/Code/school/atv_pub/2d-04-lacos/node_modules/@vitest/runner/dist/index.js:1653:12)"],"meta":{}},{"ancestorTitles":["Exercício 02"],"fullName":"Exercício 02 Ex02 - Válida - Questão 11","status":"passed","title":"Ex02 - Válida - Questão 11","duration":0.13312500000000682,"failureMessages":[],"meta":{}},{"ancestorTitles":["Exercício 02"],"fullName":"Exercício 02 Ex02 - Correta - Questão 11","status":"failed","title":"Ex02 - Correta - Questão 11","duration":0.7951620000000048,"failureMessages":["AssertionError: expected [ 'tarântula', 'escorpião', …(2) ] to deeply equal 4\n    at /home/vmca/Code/school/atv_pub/2d-04-lacos/ex02.test.js:45:30\n    at file:///home/vmca/Code/school/atv_pub/2d-04-lacos/node_modules/@vitest/runner/dist/index.js:145:11\n    at file:///home/vmca/Code/school/atv_pub/2d-04-lacos/node_modules/@vitest/runner/dist/index.js:915:26\n    at file:///home/vmca/Code/school/atv_pub/2d-04-lacos/node_modules/@vitest/runner/dist/index.js:1243:20\n    at new Promise (<anonymous>)\n    at runWithTimeout (file:///home/vmca/Code/school/atv_pub/2d-04-lacos/node_modules/@vitest/runner/dist/index.js:1209:10)\n    at file:///home/vmca/Code/school/atv_pub/2d-04-lacos/node_modules/@vitest/runner/dist/index.js:1653:37\n    at Traces.$ (file:///home/vmca/Code/school/atv_pub/2d-04-lacos/node_modules/vitest/dist/chunks/traces.CCmnQaNT.js:142:27)\n    at trace (file:///home/vmca/Code/school/atv_pub/2d-04-lacos/node_modules/vitest/dist/chunks/test.B8ej_ZHS.js:239:21)\n    at runTest (file:///home/vmca/Code/school/atv_pub/2d-04-lacos/node_modules/@vitest/runner/dist/index.js:1653:12)"],"meta":{}},{"ancestorTitles":["Exercício 02"],"fullName":"Exercício 02 Ex02 - Válida - Questão 12","status":"passed","title":"Ex02 - Válida - Questão 12","duration":0.1143160000000023,"failureMessages":[],"meta":{}},{"ancestorTitles":["Exercício 02"],"fullName":"Exercício 02 Ex02 - Correta - Questão 12","status":"failed","title":"Ex02 - Correta - Questão 12","duration":0.5133039999999767,"failureMessages":["AssertionError: expected '' to deeply equal 'sagui'\n    at /home/vmca/Code/school/atv_pub/2d-04-lacos/ex02.test.js:45:30\n    at file:///home/vmca/Code/school/atv_pub/2d-04-lacos/node_modules/@vitest/runner/dist/index.js:145:11\n    at file:///home/vmca/Code/school/atv_pub/2d-04-lacos/node_modules/@vitest/runner/dist/index.js:915:26\n    at file:///home/vmca/Code/school/atv_pub/2d-04-lacos/node_modules/@vitest/runner/dist/index.js:1243:20\n    at new Promise (<anonymous>)\n    at runWithTimeout (file:///home/vmca/Code/school/atv_pub/2d-04-lacos/node_modules/@vitest/runner/dist/index.js:1209:10)\n    at file:///home/vmca/Code/school/atv_pub/2d-04-lacos/node_modules/@vitest/runner/dist/index.js:1653:37\n    at Traces.$ (file:///home/vmca/Code/school/atv_pub/2d-04-lacos/node_modules/vitest/dist/chunks/traces.CCmnQaNT.js:142:27)\n    at trace (file:///home/vmca/Code/school/atv_pub/2d-04-lacos/node_modules/vitest/dist/chunks/test.B8ej_ZHS.js:239:21)\n    at runTest (file:///home/vmca/Code/school/atv_pub/2d-04-lacos/node_modules/@vitest/runner/dist/index.js:1653:12)"],"meta":{}}],"startTime":1776098660581,"endTime":1776098660597.5132,"status":"failed","message":"","name":"/home/vmca/Code/school/atv_pub/2d-04-lacos/ex02.test.js"}]}